twarc_videos
