Metadata-Version: 2.1
Name: twarc-videos
Version: 0.0.3
Summary: A twarc plugin to extract referenced video from tweet data
Home-page: https://github.com/docnow/twarc-videos
Author: Ed Summers
Author-email: ehs@pobox.com
License: UNKNOWN
Platform: UNKNOWN
Requires-Python: >=3.3
